[
  {
    "referrer": "github.com",
    "count": 15,
    "uniques": 14
  },
  {
    "referrer": "muyunyun.cn",
    "count": 4,
    "uniques": 4
  },
  {
    "referrer": "link.zhihu.com",
    "count": 3,
    "uniques": 3
  },
  {
    "referrer": "cnblogs.com",
    "count": 2,
    "uniques": 2
  },
  {
    "referrer": "Google",
    "count": 2,
    "uniques": 2
  },
  {
    "referrer": "segmentfault.com",
    "count": 2,
    "uniques": 2
  },
  {
    "referrer": "awesomeopensource.com",
    "count": 1,
    "uniques": 1
  }
]