[
  {
    "path": "/MuYunyun/reactSPA",
    "title": "MuYunyun/reactSPA: combination of react teconology stack",
    "count": 38,
    "uniques": 29
  },
  {
    "path": "/MuYunyun/reactSPA/tree/master/src",
    "title": "reactSPA/src at master · MuYunyun/reactSPA · GitHub",
    "count": 12,
    "uniques": 8
  },
  {
    "path": "/MuYunyun/reactSPA/tree/master/src/client",
    "title": "reactSPA/src/client at master · MuYunyun/reactSPA · GitHub",
    "count": 10,
    "uniques": 7
  },
  {
    "path": "/MuYunyun/reactSPA/tree/master/src/common",
    "title": "reactSPA/src/common at master · MuYunyun/reactSPA",
    "count": 4,
    "uniques": 4
  },
  {
    "path": "/MuYunyun/reactSPA/blob/master/src/client/index.js",
    "title": "reactSPA/index.js at master · MuYunyun/reactSPA · GitHub",
    "count": 3,
    "uniques": 3
  },
  {
    "path": "/MuYunyun/reactSPA/blob/master/src/client/middleware/logger.js",
    "title": "reactSPA/logger.js at master · MuYunyun/reactSPA · GitHub",
    "count": 3,
    "uniques": 3
  },
  {
    "path": "/MuYunyun/reactSPA/tree/master/src/client/middleware",
    "title": "reactSPA/src/client/middleware at master · MuYunyun/reactSPA · GitHub",
    "count": 3,
    "uniques": 3
  },
  {
    "path": "/MuYunyun/reactSPA/tree/master/scripts",
    "title": "reactSPA/scripts at master · MuYunyun/reactSPA · GitHub",
    "count": 3,
    "uniques": 2
  },
  {
    "path": "/MuYunyun/reactSPA/tree/gh-pages",
    "title": "MuYunyun/reactSPA at gh-pages",
    "count": 3,
    "uniques": 1
  },
  {
    "path": "/MuYunyun/reactSPA/tree/traffic",
    "title": "MuYunyun/reactSPA at traffic",
    "count": 3,
    "uniques": 1
  }
]