[
  {
    "path": "/MuYunyun/reactSPA",
    "title": "MuYunyun/reactSPA: combination of react teconology stack",
    "count": 27,
    "uniques": 23
  },
  {
    "path": "/MuYunyun/reactSPA/tree/master/src",
    "title": "reactSPA/src at master · MuYunyun/reactSPA · GitHub",
    "count": 4,
    "uniques": 3
  },
  {
    "path": "/MuYunyun/reactSPA/tree/master/src/common",
    "title": "reactSPA/src/common at master · MuYunyun/reactSPA",
    "count": 2,
    "uniques": 1
  },
  {
    "path": "/MuYunyun/reactSPA/tree/master/src/common/pages",
    "title": "reactSPA/src/common at master · MuYunyun/reactSPA",
    "count": 2,
    "uniques": 1
  },
  {
    "path": "/MuYunyun/reactSPA/tree/master/src/common/pages/music",
    "title": "reactSPA/src/common/pages/music at master · MuYunyun/reactSPA",
    "count": 2,
    "uniques": 1
  },
  {
    "path": "/MuYunyun/reactSPA/blob/master/src/common/container/header.less",
    "title": "reactSPA/header.less at master · MuYunyun/reactSPA · GitHub",
    "count": 1,
    "uniques": 1
  },
  {
    "path": "/MuYunyun/reactSPA/blob/master/src/common/pages/music/index.js",
    "title": "reactSPA/src/common/pages/music at master · MuYunyun/reactSPA",
    "count": 1,
    "uniques": 1
  },
  {
    "path": "/MuYunyun/reactSPA/issues",
    "title": "MuYunyun/reactSPA: combination of react teconology stack",
    "count": 1,
    "uniques": 1
  },
  {
    "path": "/MuYunyun/reactSPA/issues/32",
    "title": "路由问题 · Issue #32 · MuYunyun/reactSPA · GitHub",
    "count": 1,
    "uniques": 1
  },
  {
    "path": "/MuYunyun/reactSPA/issues/54",
    "title": "react 性能优化实践 · Issue #54 · MuYunyun/reactSPA · GitHub",
    "count": 1,
    "uniques": 1
  }
]